powerline_keebs/__init__.py
powerline_keebs/segments.py
powerline_keebs-0.2.3.dist-info/LICENSE
powerline_keebs-0.2.3.dist-info/METADATA
powerline_keebs-0.2.3.dist-info/WHEEL
powerline_keebs-0.2.3.dist-info/RECORD
