Metadata-Version: 2.1
Name: powerline-keebs
Version: 0.2.3
Summary: A custom Powerline segment for displaying currently connected keyboards
Home-page: https://github.com/j4ckofalltrades/powerline-keebs
License: MIT
Keywords: powerline,keyboards
Author: Jordan Duabe
Author-email: me@jduabe.dev
Requires-Python: >=3.7,<4.0
Classifier: License :: OSI Approved :: MIT License
Classifier: Programming Language :: Python :: 3
Classifier: Programming Language :: Python :: 3.7
Classifier: Programming Language :: Python :: 3.8
Classifier: Programming Language :: Python :: 3.9
Classifier: Programming Language :: Python :: 3.10
Classifier: Programming Language :: Python :: 3.11
Project-URL: Bug Tracker, https://github.com/j4ckofalltrades/powerline-keebs/issues
Project-URL: Repository, https://github.com/j4ckofalltrades/powerline-keebs
